owoifier/__init__.py
owoifier/constants.py
owoifier/owoifier.py
owoifier/_cli/__init__.py
owoifier/_cli/interface.py
owoifier-0.1.1.dist-info/LICENSE
owoifier-0.1.1.dist-info/METADATA
owoifier-0.1.1.dist-info/WHEEL
owoifier-0.1.1.dist-info/entry_points.txt
owoifier-0.1.1.dist-info/top_level.txt
owoifier-0.1.1.dist-info/RECORD
