Metadata-Version: 2.1
Name: owoifier
Version: 0.1.1
Summary: Translates English text to OwO using magic.
Home-page: https://github.com/FernOfSigma/owoifier
Author: FernOfSigma
Author-email: 90320595+FernOfSigma@users.noreply.github.com
License: GPL-3.0-or-later
Project-URL: Homepage, https://github.com/FernOfSigma/owoifier
Project-URL: Source Code, https://github.com/FernOfSigma/owoifier
Project-URL: Bug Tracker, https://github.com/FernOfSigma/owoifier/issues
Platform: UNKNOWN
Classifier: Development Status :: 3 - Alpha
Classifier: Environment :: Console
Classifier: Intended Audience :: End Users/Desktop
Classifier: License :: OSI Approved :: GNU General Public License v3 or later (GPLv3+)
Classifier: Operating System :: OS Independent
Classifier: Programming Language :: Python
Classifier: Programming Language :: Python :: 3
Classifier: Programming Language :: Python :: 3 :: Only
Classifier: Programming Language :: Python :: 3.6
Classifier: Programming Language :: Python :: 3.7
Classifier: Programming Language :: Python :: 3.9
Classifier: Programming Language :: Python :: 3.10
Classifier: Programming Language :: Python :: 3.11
Classifier: Programming Language :: Python :: Implementation :: CPython
Classifier: Topic :: Text Processing
Classifier: Typing :: Typed
License-File: LICENSE
